AsciiEngine/__init__.py
AsciiEngine/animation.py
AsciiEngine/input.py
AsciiEngine/mathutils.py
AsciiEngine/renderer.py
AsciiEngine/update.py
AsciiEngine-0.0.8.dist-info/METADATA
AsciiEngine-0.0.8.dist-info/WHEEL
AsciiEngine-0.0.8.dist-info/top_level.txt
AsciiEngine-0.0.8.dist-info/RECORD
