Metadata-Version: 2.1
Name: AsciiEngine
Version: 0.0.8
Summary: A python module for making games that run in the terminal.
Author: RetroGamer5491
Author-email: caarfken@proton.me
Requires: pynput
